<odoo>
    <record id="view_project_task_form" model="ir.ui.view">
        <field name="name">project.task.form</field>
        <field name="model">project.task</field>
        <field name="arch" type="xml">
            <form>
                <sheet>
                    <group>
                        <field name="name"/>
                        <field name="description"/>
                        <field name="user_ids" widget="many2many_tags"/>
                        <field name="project_id"/>
                        <field name="due_date"/>
                        <field name="state"/>
                        <field name="days_remaining" widget='statusbar' statusbar_visible='true'/>
                        <field name="overdue_days" widget='statusbar' statusbar_visible='true'/>
                    </group>
                    <notebook>
                        <page string="History">
                            <field name="history_ids">
                                <tree>
                                    <field name="note"/>
                                    <field name="created_at"/>
                                </tree>
                            </field>
                        </page>
                        <page string="Attachments">
                            <field name="attachment_ids">
                                <tree>
                                    <field name="name"/>
                                    <field name="file_size"/>
                                </tree>
                            </field>
                        </page>
                    </notebook>
                </sheet>
            </form>
        </field>
    </record>
</odoo>
